operaciones1/__init__.py
operaciones1/modulo.py
operaciones1-0.1.0.dist-info/METADATA
operaciones1-0.1.0.dist-info/WHEEL
operaciones1-0.1.0.dist-info/top_level.txt
operaciones1-0.1.0.dist-info/RECORD
