Metadata-Version: 2.4
Name: operaciones1
Version: 0.1.0
Summary: libreria de operaciones básicas
Author: Alexis Ruales
License: MIT
Requires-Python: >=3.11.13
Dynamic: author
Dynamic: description
Dynamic: description-content-type
Dynamic: license
Dynamic: requires-python
Dynamic: summary
